cpn_core/__init__.py
cpn_core/py.typed
cpn_core/constants/datetime.py
cpn_core/get_data/engines/base.py
cpn_core/get_data/engines/check_phat_nguoi.py
cpn_core/get_data/engines/csgt.py
cpn_core/get_data/engines/phat_nguoi.py
cpn_core/get_data/engines/zm_io.py
cpn_core/models/plate_detail.py
cpn_core/models/plate_info.py
cpn_core/models/violation_detail.py
cpn_core/notifications/engines/base.py
cpn_core/notifications/engines/discord.py
cpn_core/notifications/engines/telegram.py
cpn_core/notifications/models/base.py
cpn_core/notifications/models/discord.py
cpn_core/notifications/models/telegram.py
cpn_core/types/api.py
cpn_core/types/log_level.py
cpn_core/types/vehicle_type.py
cpn_core/utils/gen_map_search_url.py
cpn_core-0.5.0.dist-info/METADATA
cpn_core-0.5.0.dist-info/WHEEL
cpn_core-0.5.0.dist-info/licenses/LICENSE
cpn_core-0.5.0.dist-info/RECORD
